[
  {
    "image name": "디비니티2.png",
    "title": "디비니티2",
    "value": "디비니티: 오리지널 신 2를 깼다!",
    "now": 50,
    "max": 100
  },
  {
    "image name": "정처기.png",
    "title": "정보처리기사",
    "value": "정보처리기사를 취득했다!",
    "now": 50,
    "max": 100
  },
  {
    "image name": "리마1급.png",
    "title": "리눅스마스터 1급",
    "value": "리눅스마스터 1급을 취득했다!",
    "now": 0,
    "max": 100
  },
  {
    "image name": "투자자산운용사.png",
    "title": "투자자산운용사",
    "value": "투자자산운용사를 취득했다!",
    "now": 0,
    "max": 100
  },
  {
    "image name": "엘든링.webp",
    "title": "엘든링",
    "value": "엘든링을 깼다!",
    "now": 66.6,
    "max": 100
  },
  {
    "image name": "몬헌월드.webp",
    "title": "몬헌월드",
    "value": "몬스터헌터 월드의 헌터 랭크 999를 달성했다!",
    "now": 892,
    "max": 999
  },
  {
    "image name": "몬헌월드아본.webp",
    "title": "몬헌월드아본",
    "value": "몬스터헌터 월드 아이스본의 마스터 랭크 999를 달성했다!",
    "now": 510,
    "max": 999
  },
  {
    "image name": "몬헌라이즈.webp",
    "title": "몬헌라이즈",
    "value": "몬스터헌터 라이즈의 헌터 랭크 999를 달성했다!",
    "now": 256,
    "max": 999
  },
  {
    "image name": "몬헌썬브.webp",
    "title": "몬헌라이즈썬브",
    "value": "몬스터헌터 라이즈 썬브레이크의 마스터 랭크 999를 달성했다!",
    "now": 50,
    "max": 999
  },
  {
    "image name": "페이퍼플리즈.png",
    "title": "페이퍼 플리즈",
    "value": "페이퍼 플리즈를 클리어했다!",
    "now": 0,
    "max": 100
  },
  {
    "image name": "바로트라우마.jpg",
    "title": "바로트라우마",
    "value": "바로트라우마를 클리어했다!",
    "now": 0,
    "max": 100
  },
  {
    "image name": "딥락갤럭틱.webp",
    "title": "딥 락 갤럭틱",
    "value": "딥 락 갤럭틱을 클리어했다!",
    "now": 0,
    "max": 100
  },
  {
    "image name": "GTFO.png",
    "title": "GTFO",
    "value": "GTFO를 클리어했다!",
    "now": 0,
    "max": 100
  },
  {
    "image name": "휴먼폴플랫.png",
    "title": "휴먼 폴 플랫",
    "value": "휴먼 폴 플랫을 클리어했다!",
    "now": 0,
    "max": 100
  },
  {
    "image name": "오버쿡드.jpg",
    "title": "오버쿡드",
    "value": "오버쿡드를 클리어했다!",
    "now": 0,
    "max": 100
  },
  {
    "image name": "테라리아.png",
    "title": "테라리아",
    "value": "테라리아를 클리어했다!",
    "now": 100,
    "max": 100
  },
  {
    "image name": "칼라미티.jpg",
    "title": "테라리아 칼라미티 모드",
    "value": "테라리아 칼라미티 모드를 클리어했다!",
    "now": 100,
    "max": 100
  },
  {
    "image name": "Touhou Mystia Izakaya_103.ico",
    "title": "동방야작식당",
    "value": "동방야작식당을 클리어했다!",
    "now": 0,
    "max": 100
  },
  {
    "image name": "라이자의 아틀리에2.jpg",
    "title": "라이자의 아틀리에2",
    "value": "라이자의 아틀리에2를 클리어했다!",
    "now": 0,
    "max": 100
  },
  {
    "image name": "바바 이즈 유.png",
    "title": "바바 이즈 유",
    "value": "Baba Is You를 클리어했다!",
    "now": 0,
    "max": 100
  },
  {
    "image name": "Grim Dawn.png",
    "title": "그림 던",
    "value": "Grim Dawn을 클리어했다!",
    "now": 0,
    "max": 100
  },
  {
    "image name": "A Hat In Time.png",
    "title": "모자걸",
    "value": "A Hat In Time을 클리어했다!",
    "now": 0,
    "max": 100
  },
  {
    "image name": "로보토미 코퍼레이션.jpg",
    "title": "로보토미",
    "value": "로보토미 코퍼레이션을 클리어했다!",
    "now": 40,
    "max": 45
  },
  {
    "image name": "The Case of the Golden Idol.png",
    "title": "골든 아이돌",
    "value": "The Case of the Golden Idol 클리어했다!",
    "now": 0,
    "max": 100
  }
]
